{"series_id": "NG.NA1490_SAK_2.A", "name": "Alaska Natural Gas Total Consumption, Annual", "units": "Million Cubic Feet", "f": "A", "unitsshort": "MMcf", "description": "Alaska Natural Gas Total Consumption", "copyright": "None", "source": "EIA, U.S. Energy Information Administration", "iso3166": "USA-AK", "geography": "USA-AK", "start": "1997", "end": "2019", "last_updated": "2020-09-30T16:10:46-04:00", "data": [["2019", 366476], ["2018", 355132], ["2017", 347725], ["2016", 330552], ["2015", 333602], ["2014", 328945], ["2013", 332298], ["2012", 343110], ["2011", 335458], ["2010", 333312], ["2009", 342261], ["2008", 341888], ["2007", 369967], ["2006", 373850], ["2005", 432972], ["2004", 406319], ["2003", 414234], ["2002", 419131], ["2001", 408960], ["2000", 427288], ["1999", 422816], ["1998", 434871], ["1997", 425393]]}