{"series_id": "NG.NA1145_SAZ_2.A", "name": "Arizona Quantity of Production Associated with Reported Wellhead Value, Annual", "units": "Million Cubic Feet", "f": "A", "unitsshort": "MMcf", "description": "Arizona Quantity of Production Associated with Reported Wellhead Value", "copyright": "None", "source": "EIA, U.S. Energy Information Administration", "iso3166": "USA-AZ", "geography": "USA-AZ", "start": "1983", "end": "2018", "last_updated": "2020-09-30T16:10:46-04:00", "data": [["2018", 0], ["2017", 0], ["2010", 165], ["2009", 695], ["2008", 503], ["2007", 634], ["2006", 588], ["2005", 211], ["2004", 306], ["2003", 426], ["2002", 243], ["2001", 266], ["2000", 332], ["1999", 439], ["1998", 411], ["1997", 401], ["1996", 405], ["1995", 500], ["1994", 691], ["1993", 548], ["1992", 730], ["1991", 1225], ["1990", 2125], ["1989", 1360], ["1988", 0], ["1987", 0], ["1986", 0], ["1985", 0], ["1984", 10], ["1983", 26]]}