{"series_id": "NG.NA1250_SNH_2.A", "name": "New Hampshire Natural Gas Interstate Deliveries, Annual", "units": "Million Cubic Feet", "f": "A", "unitsshort": "MMcf", "description": "New Hampshire Natural Gas Interstate Deliveries", "copyright": "None", "source": "EIA, U.S. Energy Information Administration", "iso3166": "USA-NH", "geography": "USA-NH", "start": "1989", "end": "2019", "last_updated": "2020-09-30T16:10:46-04:00", "data": [["2019", 223571], ["2018", 218784], ["2017", 87181], ["2016", 87859], ["2015", 108931], ["2014", 96573], ["2013", 90665], ["2012", 72247], ["2011", 96607], ["2010", 132564], ["2009", 126880], ["2008", 115410], ["2007", 154268], ["2006", 104713], ["2005", 141095], ["2004", 105754], ["2003", 124841], ["2002", 130872], ["2001", 148119], ["2000", 139958], ["1999", 6597], ["1998", 5728], ["1997", 6433], ["1996", 5888], ["1995", 5521], ["1994", 4884], ["1993", 4962], ["1992", 5135], ["1991", 4815], ["1990", 4457], ["1989", 3657]]}