{"series_id": "NG.NA1562_SAL_4.A", "name": "Alabama Natural Gas % of Total Industrial Delivered for the Account of Others, Annual", "units": "Percent", "f": "A", "unitsshort": "%", "description": "Alabama Natural Gas % of Total Industrial Delivered for the Account of Others", "copyright": "None", "source": "EIA, U.S. Energy Information Administration", "iso3166": "USA-AL", "geography": "USA-AL", "start": "1989", "end": "2019", "last_updated": "2020-09-30T16:10:46-04:00", "data": [["2019", 76.5], ["2018", 75.8], ["2017", 73.8], ["2016", 75.4], ["2015", 76.8], ["2014", 76.7], ["2013", 76.4], ["2012", 77.9], ["2011", 76.5], ["2010", 75.2], ["2009", 72.1], ["2008", 72.8], ["2007", 76], ["2006", 76.5], ["2005", 76.4], ["2004", 79.2], ["2003", 78.8], ["2002", 78.4], ["2001", 77.9], ["2000", 77.6], ["1999", 78.2], ["1998", 76.7], ["1997", 75.4], ["1996", 77.4], ["1995", 76.6], ["1994", 72.7], ["1993", 72.6], ["1992", 70.1], ["1991", 68.6], ["1990", 66.5], ["1989", 62.5]]}