{"series_id": "NG.NA1490_SLA_2.A", "name": "Louisiana Natural Gas Total Consumption, Annual", "units": "Million Cubic Feet", "f": "A", "unitsshort": "MMcf", "description": "Louisiana Natural Gas Total Consumption", "copyright": "None", "source": "EIA, U.S. Energy Information Administration", "iso3166": "USA-LA", "geography": "USA-LA", "start": "1997", "end": "2019", "last_updated": "2020-09-30T16:10:46-04:00", "data": [["2019", 1861894], ["2018", 1738734], ["2017", 1593181], ["2016", 1591882], ["2015", 1470354], ["2014", 1423424], ["2013", 1396261], ["2012", 1482343], ["2011", 1420264], ["2010", 1354641], ["2009", 1189744], ["2008", 1238661], ["2007", 1289421], ["2006", 1217871], ["2005", 1254370], ["2004", 1281428], ["2003", 1233505], ["2002", 1341444], ["2001", 1219013], ["2000", 1536725], ["1999", 1495478], ["1998", 1569190], ["1997", 1661061]]}