{"series_id": "NG.NA1170_SSD_8.A", "name": "South Dakota Natural Gas Number of Gas and Gas Condensate Wells, Annual", "units": "Number of Elements", "f": "A", "unitsshort": "Count", "description": "South Dakota Natural Gas Number of Gas and Gas Condensate Wells", "copyright": "None", "source": "EIA, U.S. Energy Information Administration", "iso3166": "USA-SD", "geography": "USA-SD", "start": "1989", "end": "2019", "last_updated": "2020-09-30T16:10:46-04:00", "data": [["2019", 92], ["2018", 88], ["2017", 94], ["2016", 105], ["2015", 122], ["2014", 128], ["2013", 133], ["2012", 159], ["2011", 155], ["2010", 102], ["2009", 89], ["2008", 71], ["2007", 71], ["2006", 69], ["2005", 69], ["2004", 61], ["2003", 61], ["2002", 69], ["2001", 68], ["2000", 71], ["1999", 60], ["1998", 59], ["1997", 60], ["1996", 61], ["1995", 56], ["1994", 55], ["1993", 47], ["1992", 38], ["1991", 54], ["1990", 54], ["1989", 53]]}