{"series_id": "NG.NA2902_SMS_2.A", "name": "Mississippi Natural Gas Net International & Interstate Receipts, Annual", "units": "Million Cubic Feet", "f": "A", "unitsshort": "MMcf", "description": "Mississippi Natural Gas Net International & Interstate Receipts", "copyright": "None", "source": "EIA, U.S. Energy Information Administration", "iso3166": "USA-MS", "geography": "USA-MS", "start": "1988", "end": "2019", "last_updated": "2020-09-30T16:10:46-04:00", "data": [["2019", 672635], ["2018", 632084], ["2017", 559915], ["2016", 596590], ["2015", 620191], ["2014", 529400], ["2013", 500756], ["2012", 610006], ["2011", 589436], ["2010", 468302], ["2009", 339369], ["2008", 246840], ["2007", 290521], ["2006", 153503], ["2005", 237104], ["2004", 149471], ["2003", 139720], ["2002", 182680], ["2001", 250960], ["2000", -3496], ["1999", -18588], ["1998", 11621], ["1997", 40809], ["1996", -193358], ["1995", -209220], ["1994", 167621], ["1993", 122689], ["1992", 95107], ["1991", 123852], ["1990", 144773], ["1989", 127719], ["1988", 0]]}