{"series_id": "NG.NGM_EPG0_ENC_YPORT-NCA_MMCF.M", "name": "Portal, ND Compressed Natural Gas Exports to Canada, Monthly", "units": "Million Cubic Feet", "f": "M", "unitsshort": "MMcf", "description": "Portal, ND Compressed Natural Gas Exports to Canada", "copyright": "None", "source": "EIA, U.S. Energy Information Administration", "iso3166": "CAN", "geography": "CAN", "geography2": "USA-ND", "start": "201511", "end": "201610", "last_updated": "2018-10-03T13:37:35-04:00", "data": [["201610", 0], ["201512", 2], ["201511", 0]]}