{"series_id": "NG.NA1287_YOESA-NMX_2.A", "name": "Ogilby, CA Natural Gas Pipeline Exports to Mexico, Annual", "units": "Million Cubic Feet", "f": "A", "unitsshort": "MMcf", "description": "Ogilby, CA Natural Gas Pipeline Exports to Mexico", "copyright": "None", "source": "EIA, U.S. Energy Information Administration", "iso3166": "MEX", "geography": "MEX", "geography2": "USA-CA", "start": "1999", "end": "2020", "last_updated": "2021-02-26T11:28:16-05:00", "data": [["2020", 110790], ["2019", 122203], ["2018", 122836], ["2017", 108218], ["2016", 115228], ["2015", 115615], ["2014", 112077], ["2013", 99468], ["2012", 103050], ["2011", 87259], ["2010", 36683], ["2009", 95394], ["2008", 103540], ["2007", 91539], ["2006", 95710], ["2005", 85815], ["2004", 75950], ["2003", 50797], ["2002", 11450], ["2001", null], ["2000", null], ["1999", null]]}