{"series_id": "NG.NA1539_SMA_8.A", "name": "Massachusetts Natural Gas Number of Commercial Consumers - Transported, Annual", "units": "Number of Elements", "f": "A", "unitsshort": "Count", "description": "Massachusetts Natural Gas Number of Commercial Consumers - Transported", "copyright": "None", "source": "EIA, U.S. Energy Information Administration", "iso3166": "USA-MA", "geography": "USA-MA", "start": "1998", "end": "2019", "last_updated": "2020-09-30T16:10:46-04:00", "data": [["2019", 20833], ["2018", 20705], ["2017", 20120], ["2016", 19811], ["2015", 18779], ["2014", 18753], ["2013", 19283], ["2012", 18726], ["2011", 17160], ["2010", 16231], ["2006", 9696], ["2005", 7442], ["2004", 7429], ["2003", 7351], ["2002", 8844], ["2001", 10304], ["2000", 7032], ["1999", 9530], ["1998", 9236]]}