{"series_id": "NG.NA1410_SAZ_2.A", "name": "Arizona Natural Gas Balancing Item, Annual", "units": "Million Cubic Feet", "f": "A", "unitsshort": "MMcf", "description": "Arizona Natural Gas Balancing Item", "copyright": "None", "source": "EIA, U.S. Energy Information Administration", "iso3166": "USA-AZ", "geography": "USA-AZ", "start": "1997", "end": "2019", "last_updated": "2020-09-30T16:10:46-04:00", "data": [["2019", -37963], ["2018", -40844], ["2017", -19505], ["2016", 7413], ["2015", -3418], ["2014", -2926], ["2013", -1351], ["2012", -13246], ["2011", -18162], ["2010", -20750], ["2009", -15825], ["2008", 17478], ["2007", 3165], ["2006", -6821], ["2005", -2238], ["2004", 12941], ["2003", -8566], ["2002", 1505], ["2001", 3394], ["2000", 35889], ["1999", 69377], ["1998", 75220], ["1997", 12938]]}