{"series_id": "NG.NGM_EPG0_PML_YCHAP-NCA_DMCF.A", "name": "Price of Champlain, NY Natural Gas LNG Imports from Canada, Annual", "units": "Dollars per Thousand Cubic Feet", "f": "A", "unitsshort": "$/Mcf", "description": "Price of Champlain, NY Natural Gas LNG Imports from Canada", "copyright": "None", "source": "EIA, U.S. Energy Information Administration", "iso3166": "CAN", "geography": "CAN", "geography2": "USA-NY", "start": "2013", "end": "2019", "last_updated": "2021-02-26T11:28:16-05:00", "data": [["2019", 9.48], ["2018", 8.84], ["2017", 9.24], ["2016", 8.55], ["2015", 8.78], ["2014", 10.69], ["2013", null]]}