{"series_id": "NG.NA1250_SNE-SKS_2.A", "name": "Nebraska Natural Gas Interstate Deliveries to Kansas, Annual", "units": "Million Cubic Feet", "f": "A", "unitsshort": "MMcf", "description": "Nebraska Natural Gas Interstate Deliveries to Kansas", "copyright": "None", "source": "EIA, U.S. Energy Information Administration", "iso3166": "USA-KS", "geography": "USA-KS", "geography2": "USA-NE", "start": "1989", "end": "2019", "last_updated": "2020-09-30T16:10:46-04:00", "data": [["2019", 324266], ["2018", 490349], ["2017", 439475], ["2016", 407779], ["2015", 355115], ["2014", 356253], ["2013", 416921], ["2012", 561430], ["2011", 647169], ["2010", 690808], ["2009", 428090], ["2008", 257451], ["2007", 84063], ["2006", 58372], ["2005", 115323], ["2004", 72412], ["2003", 77837], ["2002", 80412], ["2001", 60663], ["2000", 60663], ["1999", 60663], ["1998", 58670], ["1997", 1400], ["1996", 1283], ["1995", 1156], ["1994", 284], ["1993", 145], ["1992", 2], ["1991", 240], ["1990", 118], ["1989", 37]]}