{"series_id": "NG.NGM_EPG0_PNG_YSPL-NSN_DMCF.A", "name": "Price of Liquefied Sabine Pass, LA Natural Gas Exports Price to Singapore, Annual", "units": "Dollars per Thousand Cubic Feet", "f": "A", "unitsshort": "$/MCF", "description": "Price of Liquefied Sabine Pass, LA Natural Gas Exports Price to Singapore", "copyright": "None", "source": "EIA, U.S. Energy Information Administration", "iso3166": "SGP", "geography": "SGP", "geography2": "USA-LA", "start": "2017", "end": "2019", "last_updated": "2021-02-26T11:28:16-05:00", "data": [["2019", 4.72], ["2018", 5.63], ["2017", null]]}