{"series_id": "NG.NGM_EPG0_ENG_YSPL-NPL_MMCF.M", "name": "Sabine Pass, LA Liquefied Natural Gas Exports to Poland, Monthly", "units": "Million Cubic Feet", "f": "M", "unitsshort": "MMcf", "description": "Sabine Pass, LA Liquefied Natural Gas Exports to Poland", "copyright": "None", "source": "EIA, U.S. Energy Information Administration", "iso3166": "POL", "geography": "POL", "geography2": "USA-LA", "start": "201705", "end": "202103", "last_updated": "2021-05-28T10:38:14-04:00", "data": [["202103", 3507], ["202102", 3387], ["202012", 3430], ["202010", 3157], ["202005", 2897], ["202004", 3523], ["201912", 3683], ["201911", 3432], ["201910", 3489], ["201908", 3537], ["201907", 3694], ["201903", 3701], ["201901", 9762], ["201705", 3440]]}