{"series_id": "NG.NGM_EPG0_IML_YCAM-NPE_MMCF.M", "name": "Cameron, LA Liquefied Natural Gas Imports from Peru, Monthly", "units": "Million Cubic Feet", "f": "M", "unitsshort": "MMcf", "description": "Cameron, LA Liquefied Natural Gas Imports from Peru", "copyright": "None", "source": "EIA, U.S. Energy Information Administration", "iso3166": "PER", "geography": "PER", "geography2": "USA-LA", "start": "201103", "end": "201104", "last_updated": "2015-03-31T23:59:10-04:00", "data": [["201104", 3368], ["201103", 3477]]}