{"series_id": "NG.NA1277_YHDGO-NMX_2.A", "name": "Hidalgo, TX Natural Gas Pipeline Imports From Mexico, Annual", "units": "Million Cubic Feet", "f": "A", "unitsshort": "MMcf", "description": "Hidalgo, TX Natural Gas Pipeline Imports From Mexico", "copyright": "None", "source": "EIA, U.S. Energy Information Administration", "iso3166": "MEX", "geography": "MEX", "geography2": "USA-TX", "start": "1996", "end": "2014", "last_updated": "2015-10-01T12:49:41-04:00", "data": [["2014", 0], ["2013", 0], ["2012", 0], ["2011", 0], ["2010", 62], ["2009", 284], ["2008", 1201], ["2007", 5259], ["2006", 967], ["2005", 1342], ["2004", 0], ["2003", 0], ["2002", 782], ["2001", 7292], ["2000", 2093], ["1999", 41879], ["1998", 13496], ["1997", 17243], ["1996", 13609]]}