{"series_id": "NG.NGM_EPG0_IML_YCHAP-Z00_MMCF.A", "name": "Champlain, NY Natural Gas Liquefied Natural Gas Imports, Annual", "units": "Million Cubic Feet", "f": "A", "unitsshort": "MMcf", "description": "Champlain, NY Natural Gas Liquefied Natural Gas Imports", "copyright": "None", "source": "EIA, U.S. Energy Information Administration", "iso3166": "USA-NY", "geography": "USA-NY", "geography2": "USA", "start": "2013", "end": "2020", "last_updated": "2021-02-26T11:28:16-05:00", "data": [["2020", 0], ["2019", 10], ["2018", 30], ["2017", 38], ["2016", 197], ["2015", 26], ["2014", 63], ["2013", 0]]}