{"series_id": "NG.NGA_EPG0_IML_YFPT-Z00_MMCF.M", "name": "Freeport, TX Natural Gas Liquefied Natural Gas Imports, Monthly", "units": "Million Cubic Feet", "f": "M", "unitsshort": "MMcf", "description": "Freeport, TX Natural Gas Liquefied Natural Gas Imports", "copyright": "None", "source": "EIA, U.S. Energy Information Administration", "iso3166": "USA-TX", "geography": "USA-TX", "geography2": "USA", "start": "201406", "end": "201809", "last_updated": "2019-11-08T10:05:45-05:00", "data": [["201809", 360], ["201510", 5992], ["201407", 2994], ["201406", 2703]]}