{"series_id": "NG.NA1240_STN-SGA_2.A", "name": "Tennessee Natural Gas Interstate Receipts From Georgia, Annual", "units": "Million Cubic Feet", "f": "A", "unitsshort": "MMcf", "description": "Tennessee Natural Gas Interstate Receipts From Georgia", "copyright": "None", "source": "EIA, U.S. Energy Information Administration", "iso3166": "USA-GA", "geography": "USA-GA", "geography2": "USA-TN", "start": "1989", "end": "2019", "last_updated": "2020-09-30T16:10:46-04:00", "data": [["2019", 7190], ["2018", 8814], ["2017", 10707], ["2016", 10708], ["2015", 10384], ["2014", 8965], ["2013", 6212], ["2012", 9129], ["2011", 11628], ["2010", 11356], ["2009", 10918], ["2008", 11397], ["2007", 12069], ["2006", 14360], ["2005", 15428], ["2004", 15832], ["2003", 13734], ["2002", 11837], ["2001", 11420], ["2000", 10762], ["1999", 9179], ["1998", 7500], ["1997", 9406], ["1996", 8129], ["1995", 6182], ["1994", 4257], ["1993", 5355], ["1992", 5599], ["1991", 7904], ["1990", 8079], ["1989", 6650]]}