{"series_id": "NG.NGM_EPG0_MID_SKY-SOK_MMCF.A", "name": "Kentucky Natural Gas Interstate Deliveries to Oklahoma, Annual", "units": "Million Cubic Feet", "f": "A", "unitsshort": "MMCF", "description": "Kentucky Natural Gas Interstate Deliveries to Oklahoma", "copyright": "None", "source": "EIA, U.S. Energy Information Administration", "iso3166": "USA-OK", "geography": "USA-OK", "geography2": "USA-KY", "start": "2018", "end": "2019", "last_updated": "2020-09-30T16:10:46-04:00", "data": [["2019", 0], ["2018", 0]]}