{"series_id": "NG.N3020NH2.A", "name": "Natural Gas Deliveries to Commercial Consumers (Including Vehicle Fuel through 1996) in New Hampshire, Annual", "units": "Million Cubic Feet", "f": "A", "unitsshort": "MMcf", "description": "Natural Gas Deliveries to Commercial Consumers (Including Vehicle Fuel through 1996) in New Hampshire", "copyright": "None", "source": "EIA, U.S. Energy Information Administration", "iso3166": "USA-NH", "geography": "USA-NH", "start": "1980", "end": "2020", "last_updated": "2021-02-26T11:28:16-05:00", "data": [["2020", 8466], ["2019", 10135], ["2018", 10129], ["2017", 9078], ["2016", 8509], ["2015", 9630], ["2014", 9412], ["2013", 9204], ["2012", 8130], ["2011", 8890], ["2010", 8406], ["2009", 9935], ["2008", 10043], ["2007", 9360], ["2006", 8494], ["2005", 9844], ["2004", 8943], ["2003", 9673], ["2002", 8768], ["2001", 7349], ["2000", 8323], ["1999", 7214], ["1998", 6808], ["1997", 7489], ["1996", 7099], ["1995", 6514], ["1994", 6412], ["1993", 6142], ["1992", 5862], ["1991", 5028], ["1990", 5073], ["1989", 5371], ["1988", 5034], ["1987", 4601], ["1986", 4438], ["1985", 4955], ["1984", 4100], ["1983", 4437], ["1982", 4414], ["1981", 4376], ["1980", 4116]]}