{"series_id": "NG.N5060AL2.A", "name": "Alabama Natural  Gas Underground Storage Withdrawals, Annual", "units": "Million Cubic Feet", "f": "A", "unitsshort": "MMcf", "description": "Alabama Natural  Gas Underground Storage Withdrawals", "copyright": "None", "source": "EIA, U.S. Energy Information Administration", "iso3166": "USA-AL", "geography": "USA-AL", "start": "1968", "end": "2020", "last_updated": "2021-02-26T11:28:16-05:00", "data": [["2020", 23286], ["2019", 29283], ["2018", 38089], ["2017", 31307], ["2016", 28210], ["2015", 29187], ["2014", 28683], ["2013", 22968], ["2012", 23651], ["2011", 15408], ["2010", 16740], ["2009", 23298], ["2008", 26756], ["2007", 19868], ["2006", 12127], ["2005", 15356], ["2004", 13867], ["2003", 6025], ["2002", 3631], ["2001", 2414], ["2000", 2452], ["1999", 2482], ["1998", 1774], ["1997", 1860], ["1996", 2125], ["1995", 1448], ["1994", 55], ["1975", 532], ["1974", 621], ["1973", 516], ["1972", 439], ["1971", 809], ["1970", 587], ["1969", 435], ["1968", 509]]}