{"series_id": "NG.NA1561_SAZ_10.A", "name": "Arizona Natural Gas Average Annual Consumption per Industrial Consumer, Annual", "units": "Thousand Cubic Feet", "f": "A", "unitsshort": "Mcf", "description": "Arizona Natural Gas Average Consumption per Industrial Consumer", "copyright": "None", "source": "EIA, U.S. Energy Information Administration", "iso3166": "USA-AZ", "geography": "USA-AZ", "start": "1973", "end": "2019", "last_updated": "2020-09-30T16:10:46-04:00", "data": [["2019", 48630], ["2018", 50179], ["2017", 50001], ["2016", 50039], ["2015", 51006], ["2014", 58262], ["2013", 57841], ["2012", 59780], ["2011", 58554], ["2010", 52297], ["2009", 46020], ["2008", 52699], ["2007", 48999], ["2006", 42020], ["2005", 39942], ["2004", 50031], ["2003", 33949], ["2002", 35153], ["2001", 42119], ["2000", 40343], ["1999", 48706], ["1998", 54780], ["1997", 58049], ["1996", 50522], ["1995", 52195], ["1994", 49844], ["1993", 40236], ["1992", 37169], ["1991", 36098], ["1990", 34941], ["1989", 58432], ["1988", 70306], ["1987", 50161], ["1986", 25110], ["1985", 19530], ["1984", 29154], ["1983", 26858], ["1982", 25098], ["1981", 38685], ["1980", 34716], ["1979", 0], ["1978", 0], ["1977", 0], ["1976", 0], ["1975", 0], ["1974", 0], ["1973", 0]]}