{"series_id": "NG.NA1590_SOK_4.A", "name": "Oklahoma Natural Gas % of Total Electric Utility Deliveries, Annual", "units": "Percent", "f": "A", "unitsshort": "%", "description": "Oklahoma Natural Gas % of Total Electric Utility Deliveries", "copyright": "None", "source": "EIA, U.S. Energy Information Administration", "iso3166": "USA-OK", "geography": "USA-OK", "start": "1993", "end": "2019", "last_updated": "2020-09-30T16:10:46-04:00", "data": [["2019", 2.99], ["2018", 2.99], ["2017", 2.47], ["2016", 2.77], ["2015", 2.65], ["2014", 2.55], ["2013", 3.02], ["2012", 3.49], ["2011", 3.49], ["2010", 3.91], ["2009", 4.14], ["2008", 4.24], ["2007", 4.19], ["2006", 4.48], ["2005", 4.13], ["2004", 3.66], ["2003", 3.83], ["2002", 3.43], ["2001", 3.26], ["2000", 3.38], ["1999", 3.67], ["1998", 3.95], ["1997", 3.33], ["1996", 4.99], ["1995", 4.82], ["1994", 5.13], ["1993", 5.73]]}