{"series_id": "NG.NA1531_SKS_8.A", "name": "Kansas Natural Gas Number of Commercial Consumers, Annual", "units": "Number of Elements", "f": "A", "unitsshort": "Count", "description": "Kansas Natural Gas Number of Commercial Consumers", "copyright": "None", "source": "EIA, U.S. Energy Information Administration", "iso3166": "USA-KS", "geography": "USA-KS", "start": "1987", "end": "2019", "last_updated": "2020-09-30T16:10:46-04:00", "data": [["2019", 85969], ["2018", 86199], ["2017", 86232], ["2016", 85947], ["2015", 86066], ["2014", 85654], ["2013", 84969], ["2012", 84673], ["2011", 84874], ["2010", 84446], ["2009", 84715], ["2008", 84703], ["2007", 85376], ["2006", 85686], ["2005", 85634], ["2004", 86640], ["2003", 88030], ["2002", 87397], ["2001", 86592], ["2000", 87007], ["1999", 86003], ["1998", 89654], ["1997", 85018], ["1996", 89168], ["1995", 88163], ["1994", 86457], ["1993", 87735], ["1992", 86840], ["1991", 86874], ["1990", 85539], ["1989", 85143], ["1988", 83810], ["1987", 82934]]}