{"series_id": "NG.NGA_EPG0_SACW0_SWY_MMCF.A", "name": "Wyoming Working Natural Gas Underground Storage Capacity, Annual", "units": "Million Cubic Feet", "f": "A", "unitsshort": "MMcf", "description": "Wyoming Working Natural Gas Underground Storage Capacity", "copyright": "None", "source": "EIA, U.S. Energy Information Administration", "iso3166": "USA-WY", "geography": "USA-WY", "start": "2008", "end": "2019", "last_updated": "2020-09-30T16:10:46-04:00", "data": [["2019", 58492], ["2018", 74605], ["2017", 73705], ["2016", 73705], ["2015", 73705], ["2014", 73705], ["2013", 73705], ["2012", 48705], ["2011", 41284], ["2010", 42134], ["2009", 42140], ["2008", 45686]]}