{"series_id": "NG.NA1531_SAK_8.A", "name": "Alaska Natural Gas Number of Commercial Consumers, Annual", "units": "Number of Elements", "f": "A", "unitsshort": "Count", "description": "Alaska Natural Gas Number of Commercial Consumers", "copyright": "None", "source": "EIA, U.S. Energy Information Administration", "iso3166": "USA-AK", "geography": "USA-AK", "start": "1986", "end": "2019", "last_updated": "2020-09-30T16:10:46-04:00", "data": [["2019", 13940], ["2018", 13870], ["2017", 13728], ["2016", 13593], ["2015", 13549], ["2014", 13399], ["2013", 13246], ["2012", 13133], ["2011", 13027], ["2010", 12998], ["2009", 13215], ["2008", 12764], ["2007", 13408], ["2006", 14384], ["2005", 14120], ["2004", 13999], ["2003", 14502], ["2002", 14342], ["2001", 14002], ["2000", 13711], ["1999", 13409], ["1998", 13176], ["1997", 12945], ["1996", 12732], ["1995", 12584], ["1994", 12475], ["1993", 12359], ["1992", 12204], ["1991", 12071], ["1990", 11921], ["1989", 11806], ["1988", 11649], ["1987", 11484], ["1986", 11]]}