{"series_id": "NG.N3035ME4.A", "name": "Percent of Industrial Natural Gas Deliveries in Maine Represented by the Price, Annual", "units": "Percent", "f": "A", "unitsshort": "%", "description": "Percent of Industrial Natural Gas Deliveries in Maine Represented by the Price", "copyright": "None", "source": "EIA, U.S. Energy Information Administration", "iso3166": "USA-ME", "geography": "USA-ME", "start": "1997", "end": "2020", "last_updated": "2021-02-26T11:28:16-05:00", "data": [["2020", null], ["2019", 8], ["2018", 8.4], ["2017", 9], ["2016", 8.4], ["2015", 5.3], ["2014", 1.9], ["2013", 0.9], ["2012", 0.4], ["2011", 0.5], ["2010", 0.6], ["2009", 1.2], ["2008", 0.8], ["2007", 0.8], ["2006", 0.9], ["2005", 3.1], ["2004", 1.7], ["2003", 10.5], ["2002", 10.7], ["2001", 8.1], ["2000", 13.1], ["1999", 78.2], ["1998", 87.4], ["1997", 91.4]]}