{"series_id": "NG.NA1145_SFL_2.A", "name": "Florida Quantity of Production Associated with Reported Wellhead Value, Annual", "units": "Million Cubic Feet", "f": "A", "unitsshort": "MMcf", "description": "Florida Quantity of Production Associated with Reported Wellhead Value", "copyright": "None", "source": "EIA, U.S. Energy Information Administration", "iso3166": "USA-FL", "geography": "USA-FL", "start": "1983", "end": "2018", "last_updated": "2020-09-30T16:10:46-04:00", "data": [["2018", 0], ["2017", 0], ["2010", null], ["2009", null], ["2008", null], ["2007", null], ["2006", null], ["2005", null], ["2004", null], ["2003", 0], ["2002", null], ["2001", 0], ["2000", 0], ["1999", 0], ["1998", 0], ["1997", 0], ["1996", 0], ["1995", 3545], ["1994", 4940], ["1993", 2612], ["1992", 3849], ["1991", 2096], ["1990", 1443], ["1989", 1437], ["1988", 1883], ["1987", 1893], ["1986", 3004], ["1985", 13162], ["1984", 18897], ["1983", 25630]]}