{"series_id": "NG.NA1250_SMA-SNH_2.A", "name": "Massachusetts Natural Gas Interstate Deliveries to New Hampshire, Annual", "units": "Million Cubic Feet", "f": "A", "unitsshort": "MMcf", "description": "Massachusetts Natural Gas Interstate Deliveries to New Hampshire", "copyright": "None", "source": "EIA, U.S. Energy Information Administration", "iso3166": "USA-NH", "geography": "USA-NH", "geography2": "USA-MA", "start": "1989", "end": "2019", "last_updated": "2020-09-30T16:10:46-04:00", "data": [["2019", 44939], ["2018", 39362], ["2017", 42892], ["2016", 45182], ["2015", 55228], ["2014", 46272], ["2013", 44845], ["2012", 52309], ["2011", 45018], ["2010", 41342], ["2009", 46256], ["2008", 51383], ["2007", 37815], ["2006", 39131], ["2005", 45553], ["2004", 37142], ["2003", 32669], ["2002", 22318], ["2001", 13493], ["2000", 15159], ["1999", 13824], ["1998", 18774], ["1997", 19585], ["1996", 19498], ["1995", 22407], ["1994", 9460], ["1993", 15135], ["1992", 14457], ["1991", 10844], ["1990", 10203], ["1989", 10864]]}