{"series_id": "NG.NA1140_SKY_3.A", "name": "Kentucky Natural Gas Wellhead Price, Annual", "units": "Dollars per Thousand Cubic Feet", "f": "A", "unitsshort": "$/Mcf", "description": "Kentucky Natural Gas Wellhead Price", "copyright": "None", "source": "EIA, U.S. Energy Information Administration", "iso3166": "USA-KY", "geography": "USA-KY", "start": "1967", "end": "2018", "last_updated": "2020-09-30T16:10:46-04:00", "data": [["2018", null], ["2017", null], ["2010", 4.47], ["2009", null], ["2008", 8.42], ["2007", 7.35], ["2006", 8.83], ["2005", 6.84], ["2004", 5.26], ["2003", 4.54], ["2002", 3.01], ["2001", 4.78], ["2000", 3.16], ["1999", 2.07], ["1998", 2.39], ["1997", 2.66], ["1996", 2.55], ["1995", 1.64], ["1994", 2.24], ["1993", 2.28], ["1992", 1.92], ["1991", 2.03], ["1990", 2.24], ["1989", 2.13], ["1988", 2.56], ["1987", 1.82], ["1986", 1.88], ["1985", 2.39], ["1984", 1.7], ["1983", 1.51], ["1982", 1.52], ["1981", 1.01], ["1980", 0.89], ["1979", 0.95], ["1978", 0.58], ["1977", 0.55], ["1976", 0.55], ["1975", 0.54], ["1974", 0.5], ["1973", 0.35], ["1972", 0.25], ["1971", 0.25], ["1970", 0.25], ["1969", 0.25], ["1968", 0.25], ["1967", 0.24]]}