{"series_id": "NG.RES_EPCCOND_R01_SMT_MMBBL.A", "name": "Montana Crude Oil + Lease Condensate Proved Reserves, Annual", "units": "Million Barrels", "f": "A", "unitsshort": "MMbbl", "description": "Montana Crude Oil + Lease Condensate Proved Reserves", "copyright": "None", "source": "EIA, U.S. Energy Information Administration", "iso3166": "USA-MT", "geography": "USA-MT", "start": "2009", "end": "2019", "last_updated": "2021-01-11T13:05:49-05:00", "data": [["2019", 298], ["2018", 279], ["2017", 302], ["2016", 287], ["2015", 326], ["2014", 445], ["2013", 413], ["2012", 388], ["2011", 384], ["2010", 369], ["2009", 343]]}