{"series_id": "NG.RL2R02SNM_1.A", "name": "New Mexico Natural Gas Plant Liquids, Reserves Adjustments, Annual", "units": "Million Barrels", "f": "A", "unitsshort": "MMbbl", "description": "New Mexico Natural Gas Plant Liquids, Reserves Adjustments", "copyright": "None", "source": "EIA, U.S. Energy Information Administration", "iso3166": "USA-NM", "geography": "USA-NM", "start": "1979", "end": "2008", "last_updated": "2014-10-16T15:14:01-04:00", "data": [["2008", -22], ["2007", 17], ["2006", 35], ["2005", -12], ["2004", -72], ["2003", 66], ["2002", -4], ["2001", -10], ["2000", -192], ["1999", -1], ["1998", 84], ["1997", -156], ["1996", 177], ["1995", -63], ["1994", 33], ["1993", -48], ["1992", 170], ["1991", -53], ["1990", -8], ["1989", 26], ["1988", -53], ["1987", 202], ["1986", 90], ["1985", -40], ["1984", -30], ["1983", 51], ["1982", 0], ["1981", 31], ["1980", 23], ["1979", 4]]}