{"series_id": "NG.RL2R54R44F_1.A", "name": "Gulf of Mexico Federal Offshore (Western) Natural Gas Plant Liquids, Expected Future Production, Annual", "units": "Million Barrels", "f": "A", "unitsshort": "MMbbl", "description": "Gulf of Mexico Federal Offshore (Western) Natural Gas Plant Liquids, Expected Future Production", "copyright": "None", "source": "EIA, U.S. Energy Information Administration", "start": "1979", "end": "2019", "last_updated": "2021-01-11T13:05:49-05:00", "data": [["2019", 14], ["2018", 25], ["2017", 20], ["2016", 25], ["2015", 28], ["2014", 30], ["2013", 41], ["2012", 35], ["2011", 0], ["2010", 0], ["2009", 0], ["2008", 7], ["2007", 4], ["2006", 9], ["2005", 9], ["2004", 13], ["2003", 17], ["2002", 28], ["2001", 25], ["2000", 27], ["1999", 24], ["1998", 21], ["1997", 27], ["1996", 27], ["1995", 27], ["1994", 25], ["1993", 34], ["1992", 34], ["1991", 26], ["1990", 21], ["1989", 21], ["1988", 26], ["1987", 29], ["1986", 36], ["1985", 34], ["1984", 36], ["1983", 17], ["1982", 12], ["1981", 5], ["1980", 6], ["1979", 2]]}