{"series_id": "NG.RNGR24SMT_1.A", "name": "Montana Natural Gas, Wet After Lease Separation Reserves Revision Decreases, Annual", "units": "Billion Cubic Feet", "f": "A", "unitsshort": "Bcf", "description": "Montana Natural Gas, Wet After Lease Separation Reserves Revision Decreases", "copyright": "None", "source": "EIA, U.S. Energy Information Administration", "iso3166": "USA-MT", "geography": "USA-MT", "start": "1979", "end": "2019", "last_updated": "2021-01-11T13:05:49-05:00", "data": [["2019", 67], ["2018", 64], ["2017", 6], ["2016", 44], ["2015", 90], ["2014", 56], ["2013", 51], ["2012", 195], ["2011", 99], ["2010", 101], ["2009", 213], ["2008", 57], ["2007", 75], ["2006", 79], ["2005", 123], ["2004", 125], ["2003", 26], ["2002", 110], ["2001", 91], ["2000", 134], ["1999", 56], ["1998", 44], ["1997", 134], ["1996", 12], ["1995", 14], ["1994", 77], ["1993", 11], ["1992", 21], ["1991", 34], ["1990", 32], ["1989", 26], ["1988", 33], ["1987", 16], ["1986", 32], ["1985", 41], ["1984", 80], ["1983", 81], ["1982", 98], ["1981", 83], ["1980", 192], ["1979", 88]]}