{"series_id": "NG.RNGR37R44F_1.A", "name": "Gulf of Mexico Federal Offshore  (Western) Nonassociated Natural Gas, Wet After Lease Separation, Reserves Extensions, Annual", "units": "Billion Cubic Feet", "f": "A", "unitsshort": "Bcf", "description": "Gulf of Mexico Federal Offshore (Western) Nonassociated Natural Gas, Wet After Lease Separation, Reserves Extensions", "copyright": "None", "source": "EIA, U.S. Energy Information Administration", "start": "1981", "end": "2019", "last_updated": "2021-01-11T13:05:49-05:00", "data": [["2019", null], ["2018", null], ["2017", null], ["2016", null], ["2015", 37], ["2014", 31], ["2013", 10], ["2012", 14], ["2011", 13], ["2010", 107], ["2009", 19], ["2008", 287], ["2007", 129], ["2006", 203], ["2005", 91], ["2004", 81], ["2003", 185], ["2002", 138], ["2001", 288], ["2000", 582], ["1999", 422], ["1998", 215], ["1997", 391], ["1996", 218], ["1995", 209], ["1994", 180], ["1993", 326], ["1992", 180], ["1991", 249], ["1990", 255], ["1989", 434], ["1988", 494], ["1987", 158], ["1986", 421], ["1982", 231], ["1981", 322]]}