{"series_id": "NG.RNGR37RNMWEST_1.A", "name": "New Mexico - West Nonassociated Natural Gas, Wet After Lease Separation, Reserves Extensions, Annual", "units": "Billion Cubic Feet", "f": "A", "unitsshort": "Bcf", "description": "New Mexico - West Nonassociated Natural Gas, Wet After Lease Separation, Reserves Extensions", "copyright": "None", "source": "EIA, U.S. Energy Information Administration", "iso3166": "USA-NM", "geography": "USA-NM", "start": "1979", "end": "2019", "last_updated": "2021-01-11T13:05:49-05:00", "data": [["2019", null], ["2018", null], ["2017", null], ["2016", null], ["2015", 43], ["2014", 56], ["2013", 7], ["2012", 103], ["2011", 222], ["2010", 150], ["2009", 130], ["2008", 110], ["2007", 168], ["2006", 446], ["2005", 610], ["2004", 908], ["2003", 976], ["2002", 930], ["2001", 772], ["2000", 1266], ["1999", 486], ["1998", 584], ["1997", 485], ["1996", 442], ["1995", 514], ["1994", 476], ["1993", 285], ["1992", 387], ["1991", 493], ["1990", 1554], ["1989", 318], ["1988", 1147], ["1987", 64], ["1986", 73], ["1985", 129], ["1984", 127], ["1983", 132], ["1982", 182], ["1981", 484], ["1980", 384], ["1979", 334]]}