{"series_id": "NG.RNGR32SCA_1.A", "name": "California Nonassociated Natural Gas, Wet After Lease Separation, Reserves Adjustments, Annual", "units": "Billion Cubic Feet", "f": "A", "unitsshort": "Bcf", "description": "California Nonassociated Natural Gas, Wet After Lease Separation, Reserves Adjustments", "copyright": "None", "source": "EIA, U.S. Energy Information Administration", "iso3166": "USA-CA", "geography": "USA-CA", "start": "1979", "end": "2019", "last_updated": "2021-01-11T13:05:49-05:00", "data": [["2019", -3], ["2018", -3], ["2017", 5], ["2016", -27], ["2015", -42], ["2014", 28], ["2013", -20], ["2012", 57], ["2011", -12], ["2010", -3], ["2009", 2], ["2008", 3], ["2007", 29], ["2006", -11], ["2005", -4], ["2004", 41], ["2003", -22], ["2002", 32], ["2001", 9], ["2000", 58], ["1999", 27], ["1998", -43], ["1997", -8], ["1996", -111], ["1995", 35], ["1994", 51], ["1993", 96], ["1992", 15], ["1991", 60], ["1990", -23], ["1989", -35], ["1988", 45], ["1987", -47], ["1986", -2], ["1980", 7], ["1979", -22]]}