{"series_id": "NG.RCRR72R3FM_1.A", "name": "Gulf of Mexico Federal Offshore Crude Oil Production from Less than 200 Meters Deep, Annual", "units": "Million Barrels", "f": "A", "unitsshort": "MMbbl", "description": "Gulf of Mexico Federal Offshore Crude Oil Production from Less than 200 Meters Deep", "copyright": "None", "source": "EIA, U.S. Energy Information Administration", "start": "1992", "end": "2007", "last_updated": "2014-10-16T15:14:01-04:00", "data": [["2007", 101], ["2006", 87], ["2005", 104], ["2004", 157], ["2003", 149], ["2002", 163], ["2001", 173], ["2000", 185], ["1999", 193], ["1998", 201], ["1997", 219], ["1996", 213], ["1995", 215], ["1994", 212], ["1993", 220], ["1992", 221]]}