{"series_id": "NG.RNGR50NUS_1.A", "name": "U.S. Associated-Dissolved Natural Gas, Wet After Lease Separation, Estimated Production from Reserves, Annual", "units": "Billion Cubic Feet", "f": "A", "unitsshort": "Bcf", "description": "U.S. Associated-Dissolved Natural Gas, Wet After Lease Separation, Estimated Production from Reserves", "copyright": "None", "source": "EIA, U.S. Energy Information Administration", "iso3166": "USA", "geography": "USA", "start": "1979", "end": "2019", "last_updated": "2021-01-11T13:05:49-05:00", "data": [["2019", 10160], ["2018", 8634], ["2017", 7210], ["2016", 6427], ["2015", 6193], ["2014", 5277], ["2013", 4114], ["2012", 3393], ["2011", 2722], ["2010", 2445], ["2009", 2556], ["2008", 2349], ["2007", 2296], ["2006", 2281], ["2005", 2432], ["2004", 2742], ["2003", 2855], ["2002", 2988], ["2001", 3193], ["2000", 3299], ["1999", 3313], ["1998", 3136], ["1997", 3022], ["1996", 2938], ["1995", 2886], ["1994", 2907], ["1993", 2868], ["1992", 3031], ["1991", 2968], ["1990", 2936], ["1989", 3099], ["1988", 3192], ["1987", 3351], ["1986", 3443], ["1985", 3454], ["1984", 3518], ["1983", 3355], ["1982", 3248], ["1981", 3316], ["1980", 3405], ["1979", 3405]]}