{"series_id": "NG.RNGR44RTX07B_1.A", "name": "Texas - RRC District 7B Associated-Dissolved Natural Gas, Wet After Lease Separation, Reserves Revision Decreases, Annual", "units": "Billion Cubic Feet", "f": "A", "unitsshort": "Bcf", "description": "Texas - RRC District 7B Associated-Dissolved Natural Gas, Wet After Lease Separation, Reserves Revision Decreases", "copyright": "None", "source": "EIA, U.S. Energy Information Administration", "iso3166": "USA-TX", "geography": "USA-TX", "start": "1979", "end": "2019", "last_updated": "2021-01-11T13:05:49-05:00", "data": [["2019", 12], ["2018", 21], ["2017", 23], ["2016", 86], ["2015", 70], ["2014", 5], ["2013", 34], ["2012", 22], ["2011", 12], ["2010", 14], ["2009", 4], ["2008", 7], ["2007", 8], ["2006", 4], ["2005", 7], ["2004", 4], ["2003", 5], ["2002", 11], ["2001", 12], ["2000", 8], ["1999", 25], ["1998", 25], ["1997", 14], ["1996", 11], ["1995", 6], ["1994", 2], ["1993", 3], ["1992", 2], ["1991", 5], ["1990", 9], ["1989", 10], ["1988", 16], ["1987", 19], ["1986", 15], ["1985", 14], ["1984", 16], ["1983", 11], ["1982", 30], ["1981", 10], ["1980", 39], ["1979", 17]]}