{"series_id": "NG.RES_EPCCOND_R10_RTX01_MMBBL.A", "name": "Texas - RRC District 1 Crude Oil + Lease Condensate Estimated Production from Reserves, Annual", "units": "Million Barrels", "f": "A", "unitsshort": "MMbbl", "description": "Texas - RRC District 1 Crude Oil + Lease Condensate Estimated Production from Reserves", "copyright": "None", "source": "EIA, U.S. Energy Information Administration", "iso3166": "USA-TX", "geography": "USA-TX", "start": "2009", "end": "2019", "last_updated": "2021-01-11T13:05:49-05:00", "data": [["2019", 244], ["2018", 229], ["2017", 212], ["2016", 229], ["2015", 270], ["2014", 263], ["2013", 192], ["2012", 112], ["2011", 44], ["2010", 15], ["2009", 10]]}