{"series_id": "NG.RNGR32RTX09_1.A", "name": "Texas - RRC District 9 Nonassociated Natural Gas, Wet After Lease Separation, Reserves Adjustments, Annual", "units": "Billion Cubic Feet", "f": "A", "unitsshort": "Bcf", "description": "Texas - RRC District 9 Nonassociated Natural Gas, Wet After Lease Separation, Reserves Adjustments", "copyright": "None", "source": "EIA, U.S. Energy Information Administration", "iso3166": "USA-TX", "geography": "USA-TX", "start": "1979", "end": "2019", "last_updated": "2021-01-11T13:05:49-05:00", "data": [["2019", 28], ["2018", 190], ["2017", -219], ["2016", -852], ["2015", -17], ["2014", 102], ["2013", 407], ["2012", -609], ["2011", 211], ["2010", 345], ["2009", 98], ["2008", -38], ["2007", 4], ["2006", -14], ["2005", -8], ["2004", -72], ["2003", -57], ["2002", 244], ["2001", 43], ["2000", -123], ["1999", 0], ["1998", -4], ["1997", 50], ["1996", -3], ["1995", -5], ["1994", -9], ["1993", 27], ["1992", -23], ["1991", -17], ["1990", 78], ["1989", -67], ["1988", 28], ["1987", -2], ["1986", 26], ["1985", -14], ["1984", 3], ["1983", -69], ["1982", 158], ["1981", 144], ["1980", -149], ["1979", -128]]}