{"series_id": "NG.RNGR35NUS_1.A", "name": "U.S. Nonassociated Natural Gas, Wet After Lease Separation, Reserves Sales, Annual", "units": "Billion Cubic Feet", "f": "A", "unitsshort": "Bcf", "description": "U.S. Nonassociated Natural Gas, Wet After Lease Separation, Reserves Sales", "copyright": "None", "source": "EIA, U.S. Energy Information Administration", "iso3166": "USA", "geography": "USA", "start": "2000", "end": "2019", "last_updated": "2021-01-11T13:05:49-05:00", "data": [["2019", 12097], ["2018", 21492], ["2017", 22619], ["2016", 17018], ["2015", 13405], ["2014", 17671], ["2013", 8453], ["2012", 8819], ["2011", 43237], ["2010", 9436], ["2009", 3813], ["2008", 7249], ["2007", 14403], ["2006", 22178], ["2005", 7977], ["2004", 10579], ["2003", 9553], ["2002", 9601], ["2001", 10733], ["2000", 14436]]}