{"series_id": "NG.RL2R54STX_1.A", "name": "Texas (with State Offshore) Natural Gas Plant Liquids, Expected Future Production, Annual", "units": "Million Barrels", "f": "A", "unitsshort": "MMbbl", "description": "Texas (with State Offshore) Natural Gas Plant Liquids, Expected Future Production", "copyright": "None", "source": "EIA, U.S. Energy Information Administration", "iso3166": "USA-TX", "geography": "USA-TX", "start": "1979", "end": "2019", "last_updated": "2021-01-11T13:05:49-05:00", "data": [["2019", 9175], ["2018", 9205], ["2017", 7584], ["2016", 6075], ["2015", 5163], ["2014", 6676], ["2013", 5653], ["2012", 4727], ["2011", 4541], ["2010", 3983], ["2009", 3432], ["2008", 3148], ["2007", 3158], ["2006", 2913], ["2005", 2723], ["2004", 2466], ["2003", 2192], ["2002", 2368], ["2001", 2318], ["2000", 2479], ["1999", 2257], ["1998", 2262], ["1997", 2376], ["1996", 2337], ["1995", 2269], ["1994", 2151], ["1993", 2211], ["1992", 2162], ["1991", 2237], ["1990", 2305], ["1989", 2270], ["1988", 2339], ["1987", 2509], ["1986", 2671], ["1985", 2610], ["1984", 2660], ["1983", 2650], ["1982", 2393], ["1981", 2285], ["1980", 2081], ["1979", 2125]]}