{"series_id": "NG.RNGR15RTX10_1.A", "name": "Texas - RRC District 10 Dry Natural Gas Reserves Sales, Annual", "units": "Billion Cubic Feet", "f": "A", "unitsshort": "Bcf", "description": "Texas - RRC District 10 Dry Natural Gas Reserves Sales", "copyright": "None", "source": "EIA, U.S. Energy Information Administration", "iso3166": "USA-TX", "geography": "USA-TX", "start": "2000", "end": "2019", "last_updated": "2021-01-11T13:05:49-05:00", "data": [["2019", 347], ["2018", 167], ["2017", 704], ["2016", 708], ["2015", 3], ["2014", 1387], ["2013", 533], ["2012", 132], ["2011", 1089], ["2010", 131], ["2009", 46], ["2008", 677], ["2007", 486], ["2006", 128], ["2005", 893], ["2004", 74], ["2003", 268], ["2002", 203], ["2001", 46], ["2000", 145]]}