{"series_id": "NG.RNGR21SNM_1.A", "name": "New Mexico Natural Gas, Wet After Lease Separation Proved Reserves, Annual", "units": "Billion Cubic Feet", "f": "A", "unitsshort": "Bcf", "description": "New Mexico Natural Gas, Wet After Lease Separation Proved Reserves", "copyright": "None", "source": "EIA, U.S. Energy Information Administration", "iso3166": "USA-NM", "geography": "USA-NM", "start": "1979", "end": "2019", "last_updated": "2021-01-11T13:05:49-05:00", "data": [["2019", 23719], ["2018", 25090], ["2017", 20858], ["2016", 14372], ["2015", 15437], ["2014", 16426], ["2013", 14567], ["2012", 14553], ["2011", 16138], ["2010", 16529], ["2009", 16644], ["2008", 17347], ["2007", 18397], ["2006", 19104], ["2005", 19344], ["2004", 19687], ["2003", 18226], ["2002", 18453], ["2001", 18559], ["2000", 18509], ["1999", 16750], ["1998", 16259], ["1997", 16700], ["1996", 17925], ["1995", 18747], ["1994", 18588], ["1993", 19939], ["1992", 20399], ["1991", 19758], ["1990", 18529], ["1989", 16597], ["1988", 18483], ["1987", 12621], ["1986", 12540], ["1985", 11438], ["1984", 12027], ["1983", 12371], ["1982", 13082], ["1981", 14562], ["1980", 13956], ["1979", 14391]]}