{"series_id": "NG.RL2R01RTX07C_1.A", "name": "Texas - RRC District 7C Natural Gas Plant Liquids, Proved Reserves, Annual", "units": "Million Barrels", "f": "A", "unitsshort": "MMbbl", "description": "Texas - RRC District 7C Natural Gas Plant Liquids, Proved Reserves", "copyright": "None", "source": "EIA, U.S. Energy Information Administration", "iso3166": "USA-TX", "geography": "USA-TX", "start": "1979", "end": "2008", "last_updated": "2014-10-16T15:14:01-04:00", "data": [["2008", 432], ["2007", 491], ["2006", 439], ["2005", 411], ["2004", 383], ["2003", 345], ["2002", 351], ["2001", 290], ["2000", 434], ["1999", 305], ["1998", 282], ["1997", 327], ["1996", 303], ["1995", 274], ["1994", 265], ["1993", 273], ["1992", 289], ["1991", 241], ["1990", 256], ["1989", 238], ["1988", 238], ["1987", 243], ["1986", 246], ["1985", 256], ["1984", 233], ["1983", 219], ["1982", 199], ["1981", 186], ["1980", 135], ["1979", 182]]}