{"series_id": "NG.RNGR14RTX10_1.A", "name": "Texas - RRC District 10 Dry Natural Gas Reserves Revision Decreases, Annual", "units": "Billion Cubic Feet", "f": "A", "unitsshort": "Bcf", "description": "Texas - RRC District 10 Dry Natural Gas Reserves Revision Decreases", "copyright": "None", "source": "EIA, U.S. Energy Information Administration", "iso3166": "USA-TX", "geography": "USA-TX", "start": "1977", "end": "2019", "last_updated": "2021-01-11T13:05:49-05:00", "data": [["2019", 1828], ["2018", 969], ["2017", 865], ["2016", 1214], ["2015", 2461], ["2014", 1101], ["2013", 1369], ["2012", 2427], ["2011", 1413], ["2010", 958], ["2009", 1060], ["2008", 781], ["2007", 315], ["2006", 639], ["2005", 616], ["2004", 705], ["2003", 333], ["2002", 262], ["2001", 404], ["2000", 467], ["1999", 888], ["1998", 560], ["1997", 340], ["1996", 335], ["1995", 331], ["1994", 224], ["1993", 333], ["1992", 304], ["1991", 276], ["1990", 386], ["1989", 300], ["1988", 352], ["1987", 572], ["1986", 396], ["1985", 390], ["1984", 319], ["1983", 471], ["1982", 547], ["1981", 466], ["1980", 390], ["1979", 449], ["1978", 463], ["1977", 264]]}