{"series_id": "NG.RNGR33RTX07B_1.A", "name": "Texas - RRC District 7B Nonassociated Natural Gas, Wet After Lease Separation, Reserves Revision Increases, Annual", "units": "Billion Cubic Feet", "f": "A", "unitsshort": "Bcf", "description": "Texas - RRC District 7B Nonassociated Natural Gas, Wet After Lease Separation, Reserves Revision Increases", "copyright": "None", "source": "EIA, U.S. Energy Information Administration", "iso3166": "USA-TX", "geography": "USA-TX", "start": "1979", "end": "2019", "last_updated": "2021-01-11T13:05:49-05:00", "data": [["2019", 15], ["2018", 34], ["2017", 328], ["2016", 131], ["2015", 17], ["2014", 209], ["2013", 313], ["2012", 24], ["2011", 417], ["2010", 295], ["2009", 152], ["2008", 176], ["2007", 161], ["2006", 212], ["2005", 158], ["2004", 16], ["2003", 26], ["2002", 48], ["2001", 17], ["2000", 63], ["1999", 154], ["1998", 14], ["1997", 55], ["1996", 115], ["1995", 15], ["1994", 8], ["1993", 10], ["1992", 5], ["1991", 43], ["1990", 11], ["1989", 24], ["1988", 18], ["1987", 35], ["1986", 17], ["1985", 16], ["1984", 34], ["1983", 52], ["1982", 56], ["1981", 26], ["1980", 65], ["1979", 126]]}