{"series_id": "NG.RNGR14SMI_1.A", "name": "Michigan Dry Natural Gas Reserves Revision Decreases, Annual", "units": "Billion Cubic Feet", "f": "A", "unitsshort": "Bcf", "description": "Michigan Dry Natural Gas Reserves Revision Decreases", "copyright": "None", "source": "EIA, U.S. Energy Information Administration", "iso3166": "USA-MI", "geography": "USA-MI", "start": "1977", "end": "2019", "last_updated": "2021-01-11T13:05:49-05:00", "data": [["2019", 110], ["2018", 34], ["2017", 73], ["2016", 410], ["2015", 221], ["2014", 90], ["2013", 139], ["2012", 1062], ["2011", 267], ["2010", 378], ["2009", 406], ["2008", 430], ["2007", 210], ["2006", 291], ["2005", 163], ["2004", 360], ["2003", 235], ["2002", 276], ["2001", 524], ["2000", 176], ["1999", 478], ["1998", 288], ["1997", 124], ["1996", 152], ["1995", 315], ["1994", 48], ["1993", 202], ["1992", 248], ["1991", 311], ["1990", 170], ["1989", 283], ["1988", 261], ["1987", 157], ["1986", 78], ["1985", 132], ["1984", 105], ["1983", 100], ["1982", 144], ["1981", 98], ["1980", 71], ["1979", 106], ["1978", 209], ["1977", 99]]}