{"series_id": "NG.RES_EPG0_R5307_SOK_BCF.A", "name": "Oklahoma Shale Proved Reserves Extensions, Annual", "units": "Billion Cubic Feet", "f": "A", "unitsshort": "Bcf", "description": "Oklahoma Shale Proved Reserves Extensions", "copyright": "None", "source": "EIA, U.S. Energy Information Administration", "iso3166": "USA-OK", "geography": "USA-OK", "start": "2009", "end": "2019", "last_updated": "2021-01-11T13:05:49-05:00", "data": [["2019", null], ["2018", null], ["2017", null], ["2016", null], ["2015", 2413], ["2014", 1821], ["2013", 1254], ["2012", 2590], ["2011", 2780], ["2010", 2380], ["2009", 2122]]}