{"series_id": "NG.RL2R54RCAJ_1.A", "name": "California--San Joaquin Basin Onshore Natural Gas Plant Liquids, Expected Future Production, Annual", "units": "Million Barrels", "f": "A", "unitsshort": "MMbbl", "description": "California--San Joaquin Basin Onshore Natural Gas Plant Liquids, Expected Future Production", "copyright": "None", "source": "EIA, U.S. Energy Information Administration", "iso3166": "USA-CA", "geography": "USA-CA", "start": "1979", "end": "2019", "last_updated": "2021-01-11T13:05:49-05:00", "data": [["2019", 57], ["2018", 65], ["2017", 67], ["2016", 60], ["2015", 69], ["2014", 96], ["2013", 85], ["2012", 77], ["2011", 78], ["2010", 98], ["2009", 113], ["2008", 97], ["2007", 103], ["2006", 100], ["2005", 110], ["2004", 94], ["2003", 78], ["2002", 68], ["2001", 51], ["2000", 63], ["1999", 59], ["1998", 57], ["1997", 79], ["1996", 77], ["1995", 77], ["1994", 71], ["1993", 81], ["1992", 79], ["1991", 71], ["1990", 82], ["1989", 91], ["1988", 96], ["1987", 102], ["1986", 104], ["1985", 115], ["1984", 100], ["1983", 111], ["1982", 118], ["1981", 51], ["1980", 74], ["1979", 74]]}