{"series_id": "NG.RNGR32RTX07B_1.A", "name": "Texas - RRC District 7B Nonassociated Natural Gas, Wet After Lease Separation, Reserves Adjustments, Annual", "units": "Billion Cubic Feet", "f": "A", "unitsshort": "Bcf", "description": "Texas - RRC District 7B Nonassociated Natural Gas, Wet After Lease Separation, Reserves Adjustments", "copyright": "None", "source": "EIA, U.S. Energy Information Administration", "iso3166": "USA-TX", "geography": "USA-TX", "start": "1979", "end": "2019", "last_updated": "2021-01-11T13:05:49-05:00", "data": [["2019", 41], ["2018", 169], ["2017", -114], ["2016", -87], ["2015", 37], ["2014", -231], ["2013", -44], ["2012", 585], ["2011", -38], ["2010", 48], ["2009", 106], ["2008", 12], ["2007", -35], ["2006", -94], ["2005", -42], ["2004", 66], ["2003", 198], ["2002", 73], ["2001", 1], ["2000", -84], ["1999", 35], ["1998", -35], ["1997", -83], ["1996", 95], ["1995", -36], ["1994", -14], ["1993", 91], ["1992", 55], ["1991", -13], ["1990", 113], ["1989", -141], ["1988", 89], ["1987", 38], ["1986", 74], ["1985", 1], ["1984", -141], ["1983", 222], ["1982", 144], ["1981", 207], ["1980", -14], ["1979", 91]]}