{"series_id": "NG.RNGR17SKS_1.A", "name": "Kansas Dry Natural Gas Reserves Extensions, Annual", "units": "Billion Cubic Feet", "f": "A", "unitsshort": "Bcf", "description": "Kansas Dry Natural Gas Reserves Extensions", "copyright": "None", "source": "EIA, U.S. Energy Information Administration", "iso3166": "USA-KS", "geography": "USA-KS", "start": "1977", "end": "2019", "last_updated": "2021-01-11T13:05:49-05:00", "data": [["2019", null], ["2018", null], ["2017", null], ["2016", null], ["2015", 62], ["2014", 271], ["2013", 375], ["2012", 310], ["2011", 62], ["2010", 27], ["2009", 24], ["2008", 78], ["2007", 149], ["2006", 93], ["2005", 108], ["2004", 47], ["2003", 78], ["2002", 71], ["2001", 46], ["2000", 58], ["1999", 24], ["1998", 23], ["1997", 54], ["1996", 59], ["1995", 78], ["1994", 102], ["1993", 98], ["1992", 35], ["1991", 198], ["1990", 68], ["1989", 37], ["1988", 60], ["1987", 76], ["1986", 151], ["1985", 71], ["1984", 115], ["1983", 51], ["1982", 77], ["1981", 107], ["1980", 97], ["1979", 147], ["1978", 209], ["1977", 219]]}