{"series_id": "NG.RNGR17SCA_1.A", "name": "California Dry Natural Gas Reserves Extensions, Annual", "units": "Billion Cubic Feet", "f": "A", "unitsshort": "Bcf", "description": "California Dry Natural Gas Reserves Extensions", "copyright": "None", "source": "EIA, U.S. Energy Information Administration", "iso3166": "USA-CA", "geography": "USA-CA", "start": "1977", "end": "2019", "last_updated": "2021-01-11T13:05:49-05:00", "data": [["2019", null], ["2018", null], ["2017", null], ["2016", null], ["2015", 84], ["2014", 0], ["2013", 3], ["2012", 8], ["2011", 73], ["2010", 12], ["2009", 450], ["2008", 101], ["2007", 16], ["2006", 176], ["2005", 129], ["2004", 100], ["2003", 55], ["2002", 93], ["2001", 210], ["2000", 112], ["1999", 58], ["1998", 47], ["1997", 68], ["1996", 16], ["1995", 30], ["1994", 63], ["1993", 58], ["1992", 27], ["1991", 9], ["1990", 68], ["1989", 51], ["1988", 39], ["1987", 44], ["1986", 80], ["1980", 74], ["1979", 60], ["1978", 162], ["1977", 89]]}