{"series_id": "NG.RNGR13RTX08_1.A", "name": "Texas - RRC District 8 Dry Natural Gas Reserves Revision Increases, Annual", "units": "Billion Cubic Feet", "f": "A", "unitsshort": "Bcf", "description": "Texas - RRC District 8 Dry Natural Gas Reserves Revision Increases", "copyright": "None", "source": "EIA, U.S. Energy Information Administration", "iso3166": "USA-TX", "geography": "USA-TX", "start": "1977", "end": "2019", "last_updated": "2021-01-11T13:05:49-05:00", "data": [["2019", 4026], ["2018", 3325], ["2017", 4375], ["2016", 2987], ["2015", 2274], ["2014", 2164], ["2013", 1154], ["2012", 1115], ["2011", 1056], ["2010", 1082], ["2009", 828], ["2008", 1054], ["2007", 690], ["2006", 511], ["2005", 464], ["2004", 697], ["2003", 546], ["2002", 745], ["2001", 431], ["2000", 864], ["1999", 1281], ["1998", 767], ["1997", 754], ["1996", 547], ["1995", 688], ["1994", 639], ["1993", 591], ["1992", 581], ["1991", 510], ["1990", 821], ["1989", 743], ["1988", 741], ["1987", 634], ["1986", 866], ["1985", 820], ["1984", 642], ["1983", 835], ["1982", 945], ["1981", 619], ["1980", 757], ["1979", 836], ["1978", 897], ["1977", 490]]}