{"series_id": "NG.RL2R02R1901F_1.A", "name": "Gulf of Mexico Federal Offshore (Central & Eastern) Natural Gas Plant Liquids, Reserves Adjustments, Annual", "units": "Million Barrels", "f": "A", "unitsshort": "MMbbl", "description": "Gulf of Mexico Federal Offshore (Central & Eastern) Natural Gas Plant Liquids, Reserves Adjustments", "copyright": "None", "source": "EIA, U.S. Energy Information Administration", "start": "1981", "end": "2008", "last_updated": "2014-10-16T15:14:01-04:00", "data": [["2008", -32], ["2007", -3], ["2006", 44], ["2005", 29], ["2004", 118], ["2003", -93], ["2002", 59], ["2001", -27], ["2000", 68], ["1999", 87], ["1998", 17], ["1997", 125], ["1996", 16], ["1995", -65], ["1994", 0], ["1993", 25], ["1992", -60], ["1991", 53], ["1990", -48], ["1989", 11], ["1988", -16], ["1987", -2], ["1986", -19], ["1981", -31]]}