{"series_id": "NG.RNGR47RTX01_1.A", "name": "Texas - RRC District 1 Associated-Dissolved Natural Gas, Wet After Lease Separation, Reserves Extensions, Annual", "units": "Billion Cubic Feet", "f": "A", "unitsshort": "Bcf", "description": "Texas - RRC District 1 Associated-Dissolved Natural Gas, Wet After Lease Separation, Reserves Extensions", "copyright": "None", "source": "EIA, U.S. Energy Information Administration", "iso3166": "USA-TX", "geography": "USA-TX", "start": "1979", "end": "2019", "last_updated": "2021-01-11T13:05:49-05:00", "data": [["2019", null], ["2018", null], ["2017", null], ["2016", null], ["2015", 294], ["2014", 902], ["2013", 771], ["2012", 1599], ["2011", 601], ["2010", 148], ["2009", 14], ["2008", 3], ["2007", 1], ["2006", 5], ["2005", 14], ["2004", 1], ["2003", 5], ["2002", 1], ["2001", 0], ["2000", 0], ["1999", 0], ["1998", 0], ["1997", 11], ["1996", 101], ["1995", 1], ["1994", 2], ["1993", 2], ["1992", 13], ["1991", 38], ["1990", 96], ["1989", 14], ["1988", 0], ["1987", 3], ["1986", 2], ["1985", 7], ["1984", 1], ["1983", 9], ["1982", 10], ["1981", 3], ["1980", 2], ["1979", 6]]}